hsbind/__init__.py
hsbind/common_utils.py
hsbind/device_bind.py
hsbind/mobile_validator.py
hsbind/network_request.py
hsbind/network_utils.py
hsbind/rsa_utils.py
hsbind/examples/__init__.py
hsbind/examples/device_bind_demo.py
HsOpenAPIDeviceBind-1.3.3.dist-info/METADATA
HsOpenAPIDeviceBind-1.3.3.dist-info/WHEEL
HsOpenAPIDeviceBind-1.3.3.dist-info/top_level.txt
HsOpenAPIDeviceBind-1.3.3.dist-info/RECORD
