Metadata-Version: 2.1
Name: HsOpenAPIDeviceBind
Version: 1.3.3
Summary: Hs Quantitative OpenAPI Device Bind
Home-page: 
Author: Hs, Inc.
Author-email: 
License: Apache License 2.0
Keywords: Hs Quantitative OpenAPI Device Bind
Requires-Python: >=3.7
Requires-Dist: PyCryptodome (==3.10.1)
Requires-Dist: netifaces (==0.11.0)
Requires-Dist: psutil (==5.9.0)
